dyana/__init__.py
dyana/__main__.py
dyana/cli.py
dyana/docker.py
dyana/loaders/__init__.py
dyana/loaders/automodel/.gitignore
dyana/loaders/automodel/Dockerfile
dyana/loaders/automodel/main.py
dyana/loaders/automodel/requirements.txt
dyana/loaders/automodel/settings.yml
dyana/loaders/base/__init__.py
dyana/loaders/base/dyana-requirements-gpu.txt
dyana/loaders/base/dyana-requirements.txt
dyana/loaders/base/dyana.py
dyana/loaders/elf/.gitignore
dyana/loaders/elf/Dockerfile
dyana/loaders/elf/Makefile
dyana/loaders/elf/main.py
dyana/loaders/elf/settings.yml
dyana/loaders/js/.gitignore
dyana/loaders/js/Dockerfile
dyana/loaders/js/main.py
dyana/loaders/js/settings.yml
dyana/loaders/loader.py
dyana/loaders/lora/.gitignore
dyana/loaders/lora/Dockerfile
dyana/loaders/lora/main.py
dyana/loaders/lora/requirements.txt
dyana/loaders/lora/settings.yml
dyana/loaders/megatron/.gitignore
dyana/loaders/megatron/Dockerfile
dyana/loaders/megatron/main.py
dyana/loaders/megatron/requirements.txt
dyana/loaders/megatron/settings.yml
dyana/loaders/npm/.gitignore
dyana/loaders/npm/Dockerfile
dyana/loaders/npm/main.py
dyana/loaders/npm/settings.yml
dyana/loaders/ollama/.gitignore
dyana/loaders/ollama/Dockerfile
dyana/loaders/ollama/main.py
dyana/loaders/ollama/requirements.txt
dyana/loaders/ollama/settings.yml
dyana/loaders/pickle/.gitignore
dyana/loaders/pickle/Dockerfile
dyana/loaders/pickle/Makefile
dyana/loaders/pickle/main.py
dyana/loaders/pickle/settings.yml
dyana/loaders/pip/.gitignore
dyana/loaders/pip/Dockerfile
dyana/loaders/pip/main.py
dyana/loaders/pip/settings.yml
dyana/loaders/python/.gitignore
dyana/loaders/python/Dockerfile
dyana/loaders/python/Makefile
dyana/loaders/python/main.py
dyana/loaders/python/requirements.txt
dyana/loaders/python/settings.yml
dyana/loaders/settings.py
dyana/loaders/settings_test.py
dyana/loaders/website/.gitignore
dyana/loaders/website/Dockerfile
dyana/loaders/website/main.py
dyana/loaders/website/settings.yml
dyana/tracer/__init__.py
dyana-0.1.4.dist-info/LICENSE
dyana-0.1.4.dist-info/METADATA
dyana-0.1.4.dist-info/WHEEL
dyana-0.1.4.dist-info/entry_points.txt
dyana-0.1.4.dist-info/RECORD
