Metadata-Version: 2.1
Name: dyana
Version: 0.1.4
Summary: A sandbox environment based on Docker and eBPF to load and profile a wide range of file types.
Home-page: https://github.com/dreadnode/dyana
License: MIT
Author: Simone Margaritelli
Author-email: simone@dreadnode.io
Requires-Python: >=3.10,<4.0
Classifier: License :: OSI Approved :: MIT License
Classifier: Programming Language :: Python :: 3
Classifier: Programming Language :: Python :: 3.10
Classifier: Programming Language :: Python :: 3.11
Classifier: Programming Language :: Python :: 3.12
Classifier: Programming Language :: Python :: 3.13
Requires-Dist: cysimdjson (==23.8)
Requires-Dist: docker (>=7.1.0,<8.0.0)
Requires-Dist: pydantic (>=2.9.2,<3.0.0)
Requires-Dist: pydantic-yaml (>=1.4.0,<2.0.0)
Requires-Dist: rich (>=13.9.4,<14.0.0)
Requires-Dist: typer (>=0.12.5,<0.13.0)
Project-URL: Repository, https://github.com/dreadnode/dyana
